staticpython/__init__.py
staticpython/_version.py
staticpython/core.py
staticpython-0.0.1.dist-info/LICENSE
staticpython-0.0.1.dist-info/METADATA
staticpython-0.0.1.dist-info/WHEEL
staticpython-0.0.1.dist-info/top_level.txt
staticpython-0.0.1.dist-info/RECORD
